multifocal_stitching/__init__.py
multifocal_stitching/__main__.py
multifocal_stitching/merge_imgs.py
multifocal_stitching/stitching.py
multifocal_stitching/utils.py
multifocal_stitching-0.2.1.dist-info/LICENSE
multifocal_stitching-0.2.1.dist-info/METADATA
multifocal_stitching-0.2.1.dist-info/WHEEL
multifocal_stitching-0.2.1.dist-info/top_level.txt
multifocal_stitching-0.2.1.dist-info/RECORD
