Metadata-Version: 2.1
Name: multifocal-stitching
Version: 0.2.1
Summary: Algorithms and tools for stitching microscopy images taken at different focal lengths
Author-email: Chenyang Yuan <yuanchenyang@gmail.com>
Maintainer-email: Chenyang Yuan <yuanchenyang@gmail.com>
License: Copyright 2023 Chenyang Yuan
Project-URL: Homepage, https://github.com/yuanchenyang/multifocal-stitching
Project-URL: Bug Tracker, https://github.com/yuanchenyang/multifocal-stitching/issues
Project-URL: Documentation, https://github.com/yuanchenyang/multifocal-stitching
Project-URL: Source, https://github.com/yuanchenyang/multifocal-stitching
Classifier: Development Status :: 3 - Alpha
Classifier: License :: OSI Approved :: MIT License
Classifier: Programming Language :: Python :: 3
Classifier: Operating System :: OS Independent
Requires-Python: >=3.7
License-File: LICENSE
Requires-Dist: numpy
Requires-Dist: scipy
Requires-Dist: scikit-learn
Requires-Dist: opencv-python
Requires-Dist: Pillow
Provides-Extra: dev
Requires-Dist: build ; extra == 'dev'
Requires-Dist: twine ; extra == 'dev'
Provides-Extra: test
Requires-Dist: pytest ; extra == 'test'
Requires-Dist: pytest-cov ; extra == 'test'
Provides-Extra: webapp
Requires-Dist: gradio ; extra == 'webapp'
Requires-Dist: matplotlib ; extra == 'webapp'
